CHANGELOG.rst
MANIFEST.in
README.md
dev-requirements.txt
doc-requirements.txt
requirements.txt
setup.cfg
setup.py
km3like/__init__.py
km3like/data.py
km3like/ingred.py
km3like/llh.py
km3like/sample.py
km3like/sim.py
km3like.egg-info/PKG-INFO
km3like.egg-info/SOURCES.txt
km3like.egg-info/dependency_links.txt
km3like.egg-info/requires.txt
km3like.egg-info/top_level.txt