Metadata-Version: 1.0
Name: km3like
Version: 0.4
Summary: Likelihood Utils
Home-page: http://git.km3net.de/moritz/km3like
Author: Moritz Lotze
Author-email: mlotze@km3net.de
License: BSD-3
Platform: UNKNOWN
